<?xml version="1.0" encoding="UTF-8"?>
<p:FatturaElettronica versione="1.0" 
xmlns:ds="http://www.w3.org/2000/09/xmldsig#" 
xmlns:p="http://www.fatturapa.gov.it/sdi/fatturapa/v1.0" 
xmlns:xsi="http://www.w3.org/2001/XMLSchema-instance">
  <FatturaElettronicaHeader>
    <DatiTrasmissione>
      <IdTrasmittente>
        <IdPaese></IdPaese>
        <IdCodice></IdCodice>
      </IdTrasmittente>
      <ProgressivoInvio></ProgressivoInvio>
      <FormatoTrasmissione></FormatoTrasmissione>
      <CodiceDestinatario></CodiceDestinatario>
      <ContattiTrasmittente>
        <Telefono></Telefono>
        <Email></Email>
      </ContattiTrasmittente>
    </DatiTrasmissione>
    <CedentePrestatore>
      <DatiAnagrafici>
        <IdFiscaleIVA>
          <IdPaese></IdPaese>
          <IdCodice></IdCodice>
        </IdFiscaleIVA>
        <Anagrafica>
          <Denominazione></Denominazione>
        </Anagrafica>
        <RegimeFiscale></RegimeFiscale>
      </DatiAnagrafici>
      <Sede>
        <Indirizzo></Indirizzo>
        <CAP></CAP>
        <Comune></Comune>
        <Provincia></Provincia>
        <Nazione></Nazione>
      </Sede>
    </CedentePrestatore>
    <CessionarioCommittente>
      <DatiAnagrafici>
        <CodiceFiscale></CodiceFiscale>
        <Anagrafica>
          <Denominazione></Denominazione>
        </Anagrafica>
      </DatiAnagrafici>
      <Sede>
        <Indirizzo></Indirizzo>
        <CAP></CAP>
        <Comune></Comune>
        <Provincia></Provincia>
        <Nazione></Nazione>
      </Sede>
    </CessionarioCommittente>
    <SoggettoEmittente></SoggettoEmittente>
  </FatturaElettronicaHeader>  
  <FatturaElettronicaBody>
    <DatiGenerali>
        <DatiGeneraliDocumento>
            <TipoDocumento></TipoDocumento>
            <Divisa></Divisa>
            <Data></Data>
            <Numero></Numero>
            <Art73></Art73>
        </DatiGeneraliDocumento>
        <DatiOrdineAcquisto>
            <RiferimentoNumeroLinea></RiferimentoNumeroLinea>
            <IdDocumento></IdDocumento>
            <CodiceCUP></CodiceCUP>
            <CodiceCIG></CodiceCIG>
        </DatiOrdineAcquisto>
        <DatiContratto>
            <RiferimentoNumeroLinea></RiferimentoNumeroLinea>
            <IdDocumento></IdDocumento>
            <Data></Data>
            <NumItem></NumItem>
            <CodiceCUP></CodiceCUP>
            <CodiceCIG></CodiceCIG>
        </DatiContratto>
        <DatiConvenzione>
            <RiferimentoNumeroLinea></RiferimentoNumeroLinea>
            <IdDocumento></IdDocumento>
            <Data></Data>
            <NumItem></NumItem>
            <CodiceCUP></CodiceCUP>
            <CodiceCIG></CodiceCIG>
        </DatiConvenzione>
        <DatiRicezione>
            <RiferimentoNumeroLinea></RiferimentoNumeroLinea>
            <IdDocumento></IdDocumento>
            <Data></Data>
            <NumItem></NumItem>
            <CodiceCUP></CodiceCUP>
            <CodiceCIG></CodiceCIG>
        </DatiRicezione>
        <DatiTrasporto>
            <DatiAnagraficiVettore>             
                <IdFiscaleIVA>
                    <IdPaese></IdPaese>
                    <IdCodice></IdCodice>
                </IdFiscaleIVA>
                <Anagrafica>
                    <Denominazione></Denominazione>
                </Anagrafica>
            </DatiAnagraficiVettore>
            <DataOraConsegna></DataOraConsegna>
        </DatiTrasporto>
    </DatiGenerali>
    <DatiBeniServizi>
        <DettaglioLinee>
            <NumeroLinea></NumeroLinea>
            <Descrizione></Descrizione>
            <PrezzoUnitario></PrezzoUnitario>
            <PrezzoTotale></PrezzoTotale>
            <AliquotaIVA></AliquotaIVA>
        </DettaglioLinee>
        <DatiRiepilogo>
            <AliquotaIVA></AliquotaIVA>
            <ImponibileImporto></ImponibileImporto>
            <Imposta></Imposta>
        </DatiRiepilogo>
    </DatiBeniServizi>
    <DatiPagamento>
      <CondizioniPagamento></CondizioniPagamento>
      <DettaglioPagamento>
        <ModalitaPagamento></ModalitaPagamento>
        <DataScadenzaPagamento></DataScadenzaPagamento>
        <ImportoPagamento></ImportoPagamento>
      </DettaglioPagamento>
    </DatiPagamento>
  </FatturaElettronicaBody>
</p:FatturaElettronica>
