<?xml version="1.0" ?>
<odoo>

    <record id="view_account_config_settings" model="ir.ui.view">
        <field name="name">view_account_config_settings</field>
        <field name="model">res.config.settings</field>
        <field name="inherit_id" ref="base_setup.res_config_settings_view_form"/>
        <field name="arch" type="xml">
            <div id="eu_service" position="after">
                <div class="col-xs-12 col-md-6 o_setting_box"
                     title="Configuration for Split Payment module">
                    <div class="o_setting_left_pane"/>
                    <div class="o_setting_right_pane">
                        <label for="sp_account_id"/>
                        <span class="fa fa-lg fa-building-o"
                              title="Configuration for Split Payment module."
                              groups="base.group_multi_company"/>
                        <div class="text-muted">
                           Configuration for Split Payment module.
                        </div>
                        <div class="content-group">
                            <div class="row mt16">
                                <label string="Account" for="sp_account_id" class="col-md-3 o_light_label"/>
                                <field name="sp_account_id"/>
                            </div>
                        </div>
                    </div>
                </div>
            </div>

        </field>
    </record>

</odoo>
